sitepages/__init__.py
sitepages/attribute.py
sitepages/page.py
sitepages/proxy.py
sitepages-0.4.dist-info/LICENSE
sitepages-0.4.dist-info/METADATA
sitepages-0.4.dist-info/WHEEL
sitepages-0.4.dist-info/entry_points.txt
sitepages-0.4.dist-info/top_level.txt
sitepages-0.4.dist-info/zip-safe
sitepages-0.4.dist-info/RECORD
