Metadata-Version: 2.1
Name: sitepages
Version: 0.4
Summary: Web request module
Home-page: https://github.com/bondbox/sitepages/
Author: Mingzhe Zou
Author-email: zoumingzhe@outlook.com
License: GPLv2
Project-URL: Source Code, https://github.com/bondbox/sitepages/
Project-URL: Bug Tracker, https://github.com/bondbox/sitepages/issues
Project-URL: Documentation, https://github.com/bondbox/sitepages/
Keywords: command-line,argparse,argcomplete
Platform: any
Classifier: Programming Language :: Python
Classifier: Programming Language :: Python :: 3
Requires-Python: >=3.8
License-File: LICENSE
Requires-Dist: xkits-lib >=0.1
Requires-Dist: beautifulsoup4
Requires-Dist: requests
